ChordReviewsVis/ChordReviews.py
ChordReviewsVis/__init__.py
ChordReviewsVis-0.3.3.dist-info/License.txt
ChordReviewsVis-0.3.3.dist-info/METADATA
ChordReviewsVis-0.3.3.dist-info/WHEEL
ChordReviewsVis-0.3.3.dist-info/top_level.txt
ChordReviewsVis-0.3.3.dist-info/RECORD
