Metadata-Version: 2.1
Name: ChordReviewsVis
Version: 0.3.3
Summary: Process reviews data, apply text preprocessing, and generate a chord plot visualization showing word co-occurrence patterns and sentiment analysis.
Home-page: https://github.com/felix-funes/ChordReviewsVis
Project-URL: GitHub, https://github.com/felix-funes/ChordReviewsVis
Keywords: customer reviews,sentiment analysis,chord plot
License-File: License.txt
Requires-Dist: pandas
Requires-Dist: numpy
Requires-Dist: nltk
Requires-Dist: beautifulsoup4
Requires-Dist: networkx
Requires-Dist: matplotlib
Requires-Dist: holoviews
